pynsodm/__init__.py
pynsodm/exceptions/__init__.py
pynsodm/exceptions/list_item_exception.py
pynsodm/exceptions/nonexistent_id_exception.py
pynsodm/exceptions/validate_exception.py
pynsodm/fields/__init__.py
pynsodm/fields/base_field.py
pynsodm/fields/datetime_field.py
pynsodm/fields/id_fields.py
pynsodm/fields/list_field.py
pynsodm/fields/one_to_many_relation_field.py
pynsodm/fields/one_to_many_resolver_field.py
pynsodm/fields/one_to_one_relation_field.py
pynsodm/fields/one_to_one_resolver_field.py
pynsodm/fields/string_field.py
pynsodm/handlers/__init__.py
pynsodm/handlers/strings.py
pynsodm/json_ext/__init__.py
pynsodm/json_ext/encoders.py
pynsodm/rethinkdb_ext/__init__.py
pynsodm/rethinkdb_ext/base_model.py
pynsodm/rethinkdb_ext/storage.py
pynsodm/valids/__init__.py
pynsodm/valids/strings.py
pynsodm-0.3.5.dist-info/LICENSE
pynsodm-0.3.5.dist-info/METADATA
pynsodm-0.3.5.dist-info/WHEEL
pynsodm-0.3.5.dist-info/top_level.txt
pynsodm-0.3.5.dist-info/zip-safe
pynsodm-0.3.5.dist-info/RECORD
