Metadata-Version: 2.1
Name: pynsodm
Version: 0.3.5
Summary: Smart ODM for NoSQL (RethinkDB, Redis, etc.)
Home-page: https://github.com/agratoth/pynsodm
Maintainer: Anton Berdnikov
Maintainer-email: agratoth@yandex.ru
License: UNKNOWN
Platform: UNKNOWN
Classifier: License :: OSI Approved :: MIT License
Classifier: Operating System :: OS Independent
Classifier: Programming Language :: Python
Classifier: Programming Language :: Python :: 3.8
Classifier: Programming Language :: Python :: 3.9
Classifier: Topic :: Database
Classifier: Topic :: Database :: Front-Ends
Requires-Python: >=3.8
Requires-Dist: python-dotenv (>=0.15.0)
Requires-Dist: pytz (>=2021.1)
Requires-Dist: rethinkdb (>=2.4.8)
Requires-Dist: validators (>=0.18.2)
